ICT_KW/ICT_KW.py
ICT_KW/__init__.py
ICT_KW-0.0.111.dist-info/METADATA
ICT_KW-0.0.111.dist-info/WHEEL
ICT_KW-0.0.111.dist-info/top_level.txt
ICT_KW-0.0.111.dist-info/RECORD
