Metadata-Version: 2.1
Name: ICT-KW
Version: 0.0.111
Summary: ICT_KW package
Author: Ibrahim Abdullah Almayyas
Author-email: <i.almayyas.work@hotmail.com>
Keywords: python,GUI,Kuwait,Learning
Classifier: Development Status :: 1 - Planning
Classifier: Intended Audience :: Developers
Classifier: Programming Language :: Python :: 3
Classifier: Operating System :: Unix
Classifier: Operating System :: MacOS :: MacOS X
Classifier: Operating System :: Microsoft :: Windows
Requires-Dist: opencv-python
Requires-Dist: pillow
